fauxmo/__init__.py
fauxmo/cli.py
fauxmo/fauxmo.py
fauxmo/protocols.py
fauxmo/utils.py
fauxmo/plugins/__init__.py
fauxmo/plugins/commandlineplugin.py
fauxmo/plugins/homeassistantplugin.py
fauxmo/plugins/simplehttpplugin.py
fauxmo-0.8.0.dist-info/AUTHORS.md
fauxmo-0.8.0.dist-info/LICENSE
fauxmo-0.8.0.dist-info/METADATA
fauxmo-0.8.0.dist-info/WHEEL
fauxmo-0.8.0.dist-info/entry_points.txt
fauxmo-0.8.0.dist-info/top_level.txt
fauxmo-0.8.0.dist-info/RECORD
