Metadata-Version: 2.1
Name: fauxmo
Version: 0.8.0
Summary: Emulated Belkin WeMo devices that work with the Amazon Echo
Author-email: Nathan Henrie <nate@n8henrie.com>
License: MIT
Project-URL: homepage, https://github.com/n8henrie/fauxmo
Keywords: fauxmo,alexa,amazon,echo
Classifier: Natural Language :: English
Classifier: Programming Language :: Python :: 3.8
Classifier: Programming Language :: Python :: 3.9
Classifier: Programming Language :: Python :: 3.10
Classifier: Programming Language :: Python :: 3.11
License-File: LICENSE
License-File: AUTHORS.md
Provides-Extra: dev
Requires-Dist: build ==0.10.0 ; extra == 'dev'
Requires-Dist: recommonmark ==0.7.1 ; extra == 'dev'
Requires-Dist: Sphinx ==5.3.0 ; extra == 'dev'
Requires-Dist: sphinx-rtd-theme ==1.2.0 ; extra == 'dev'
Requires-Dist: twine ==4.0.2 ; extra == 'dev'
Requires-Dist: wheel ==0.38.4 ; extra == 'dev'
Provides-Extra: test
Requires-Dist: black ==23.1.0 ; extra == 'test'
Requires-Dist: coverage ==7.4.1 ; extra == 'test'
Requires-Dist: flake8-docstrings ==1.7.0 ; extra == 'test'
Requires-Dist: flake8-import-order ==0.18.2 ; extra == 'test'
Requires-Dist: flake8 ==6.0.0 ; extra == 'test'
Requires-Dist: httpbin ==0.7.0 ; extra == 'test'
Requires-Dist: isort ==5.12.0 ; extra == 'test'
Requires-Dist: mypy ==1.0.1 ; extra == 'test'
Requires-Dist: pep8-naming ==0.13.3 ; extra == 'test'
Requires-Dist: pytest ==7.2.1 ; extra == 'test'
Requires-Dist: requests ==2.29.0 ; extra == 'test'
Requires-Dist: werkzeug ==2.0.3 ; extra == 'test'
Requires-Dist: tox ==4.4.6 ; extra == 'test'
